miresearch/__init__.py
miresearch/mi_config.py
miresearch/mi_subject.py
miresearch/mi_utils.py
miresearch/miresearch.conf
miresearch/miresearch_main.py
miresearch/miresearch_watchdog.py
imaging_research-0.1.5.dist-info/LICENSE
imaging_research-0.1.5.dist-info/METADATA
imaging_research-0.1.5.dist-info/WHEEL
imaging_research-0.1.5.dist-info/entry_points.txt
imaging_research-0.1.5.dist-info/top_level.txt
imaging_research-0.1.5.dist-info/RECORD
