Metadata-Version: 2.1
Name: imaging-research
Version: 0.1.5
Summary: Medical Imaginging Research structuring and automation
Home-page: https://github.com/fraser29/miresearch
Author: Fraser M. Callaghan
Author-email: callaghan.fm@gmail.com
License: MIT
Keywords: medical,imaging,mri,ct,dicom
Classifier: License :: OSI Approved :: MIT License
Classifier: Programming Language :: Python
Classifier: Programming Language :: Python :: 3
Classifier: Programming Language :: Python :: 3.9
Classifier: Programming Language :: Python :: Implementation :: CPython
Classifier: Programming Language :: Python :: Implementation :: PyPy
Requires-Python: >=3.9.0
License-File: LICENSE
Requires-Dist: spydcmtk
Requires-Dist: pandas
Requires-Dist: numpy
Requires-Dist: watchdog
